quilt_stack_installer/VERSION
quilt_stack_installer/__init__.py
quilt_stack_installer/cli.py
quilt_stack_installer/cli_input.py
quilt_stack_installer/cloudformation.py
quilt_stack_installer/config.py
quilt_stack_installer/install_flow.py
quilt_stack_installer/route53.py
quilt_stack_installer/session_log.py
quilt_stack_installer/user_input_params.py
quilt_stack_installer-1.0.0.dist-info/METADATA
quilt_stack_installer-1.0.0.dist-info/WHEEL
quilt_stack_installer-1.0.0.dist-info/entry_points.txt
quilt_stack_installer-1.0.0.dist-info/top_level.txt
quilt_stack_installer-1.0.0.dist-info/RECORD
